odoo8_addon_product_gtin-8.0.1.1.0.99.dev6-py2.7-nspkg.pth
odoo8_addon_product_gtin-8.0.1.1.0.99.dev6.dist-info/DESCRIPTION.rst
odoo8_addon_product_gtin-8.0.1.1.0.99.dev6.dist-info/METADATA
odoo8_addon_product_gtin-8.0.1.1.0.99.dev6.dist-info/RECORD
odoo8_addon_product_gtin-8.0.1.1.0.99.dev6.dist-info/WHEEL
odoo8_addon_product_gtin-8.0.1.1.0.99.dev6.dist-info/metadata.json
odoo8_addon_product_gtin-8.0.1.1.0.99.dev6.dist-info/namespace_packages.txt
odoo8_addon_product_gtin-8.0.1.1.0.99.dev6.dist-info/top_level.txt
odoo_addons/product_gtin/__init__.py
odoo_addons/product_gtin/__openerp__.py
odoo_addons/product_gtin/product_gtin.py
odoo_addons/product_gtin/product_view.xml
odoo_addons/product_gtin/i18n/ca.po
odoo_addons/product_gtin/i18n/de.po
odoo_addons/product_gtin/i18n/es.po
odoo_addons/product_gtin/i18n/fr.po
odoo_addons/product_gtin/i18n/fr_BE.po
odoo_addons/product_gtin/i18n/product_gtin.pot
odoo_addons/product_gtin/i18n/sl.po
odoo_addons/product_gtin/i18n/sv.po
odoo_addons/product_gtin/static/description/icon.png
odoo_addons/product_gtin/tests/__init__.py
odoo_addons/product_gtin/tests/test_product_gtin_functions.py
