Metadata-Version: 2.0
Name: odoo8-addon-product-gtin
Version: 8.0.1.1.0.99.dev6
Summary: Product GTIN EAN8 EAN13 UPC JPC Support
Home-page: http://www.chricar.at/ChriCar
Author: ChriCar Beteiligungs- und Beratungs- GmbH,Odoo Community Association (OCA)
Author-email: support@odoo-community.org
License: AGPL-3
Platform: UNKNOWN
Classifier: Programming Language :: Python
Classifier: Framework :: Odoo
Classifier: License :: OSI Approved :: GNU Affero General Public License v3
Requires-Python: ~=2.7
Requires-Dist: odoo (<9.0a,>=8.0a)
